{
    "taskDefinitionArn": "arn:aws:ecs:us-west-2:697224503783:task-definition/raccoonsvsotters-def:11",
    "containerDefinitions": [
        {
            "name": "raccoonsvsotters",
            "image": "697224503783.dkr.ecr.us-west-2.amazonaws.com/raccoonsvsotters:28b80d0c9585ea9283a37bc2f86c3f6fba862b18",
            "cpu": 0,
            "portMappings": [
                {
                    "name": "raccoonsvsotters-80-tcp",
                    "containerPort": 80,
                    "hostPort": 80,
                    "protocol": "tcp",
                    "appProtocol": "http"
                }
            ],
            "essential": true,
            "environment": [],
            "mountPoints": [],
            "volumesFrom": [],
            "logConfiguration": {
                "logDriver": "awslogs",
                "options": {
                    "awslogs-create-group": "true",
                    "awslogs-group": "/ecs/raccoonsvsotters-def",
                    "awslogs-region": "us-west-2",
                    "awslogs-stream-prefix": "ecs"
                }
            }
        }
    ],
    "family": "raccoonsvsotters-def",
    "executionRoleArn": "arn:aws:iam::697224503783:role/ecsTaskExecutionRole",
    "networkMode": "awsvpc",
    "revision": 11,
    "volumes": [],
    "status": "ACTIVE",
    "requiresAttributes": [
        {
            "name": "com.amazonaws.ecs.capability.logging-driver.awslogs"
        },
        {
            "name": "ecs.capability.execution-role-awslogs"
        },
        {
            "name": "com.amazonaws.ecs.capability.ecr-auth"
        },
        {
            "name": "com.amazonaws.ecs.capability.docker-remote-api.1.19"
        },
        {
            "name": "ecs.capability.execution-role-ecr-pull"
        },
        {
            "name": "com.amazonaws.ecs.capability.docker-remote-api.1.18"
        },
        {
            "name": "ecs.capability.task-eni"
        },
        {
            "name": "com.amazonaws.ecs.capability.docker-remote-api.1.29"
        }
    ],
    "placementConstraints": [],
    "compatibilities": [
        "EC2",
        "FARGATE"
    ],
    "requiresCompatibilities": [
        "FARGATE"
    ],
    "cpu": "1024",
    "memory": "3072",
    "runtimePlatform": {
        "cpuArchitecture": "X86_64",
        "operatingSystemFamily": "LINUX"
    },
    "registeredAt": "2023-06-04T13:38:00.997Z",
    "registeredBy": "arn:aws:iam::697224503783:user/ecr-user",
    "tags": []
}
